LICENSE.txt
README.md
setup.cfg
setup.py
Topsis_Arjun_102017005/__init__.py
Topsis_Arjun_102017005/topsis_arjun_102017005.py
Topsis_Arjun_102017005.egg-info/PKG-INFO
Topsis_Arjun_102017005.egg-info/SOURCES.txt
Topsis_Arjun_102017005.egg-info/dependency_links.txt
Topsis_Arjun_102017005.egg-info/entry_points.txt
Topsis_Arjun_102017005.egg-info/requires.txt
Topsis_Arjun_102017005.egg-info/top_level.txt