Metadata-Version: 2.1
Name: Topsis-Arjun-102017005
Version: 1.0.1
Summary: A Python package for Multiple Criteria Decision Analysis (MCDA) using TOPSIS Method made by Arjun Khanchandani.
Author: Arjun Khanchandani
Author-email: <akhanchandani_be20@thapar.edu>
Keywords: python,topsis,mcda
Classifier: Development Status :: 1 - Planning
Classifier: Intended Audience :: Developers
Classifier: Programming Language :: Python :: 3
Classifier: Operating System :: Unix
Classifier: Operating System :: MacOS :: MacOS X
Classifier: Operating System :: Microsoft :: Windows
License-File: LICENSE.txt
